<?xml version="1.0" encoding="UTF-8"?>
<!DOCTYPE mapper PUBLIC "-//mybatis.org//DTD Mapper 3.0//EN" "http://mybatis.org/dtd/mybatis-3-mapper.dtd">
<mapper namespace="com.dllg.ebpay.dao.generator.JsonDataMapper">
  <resultMap id="BaseResultMap" type="com.dllg.ebpay.model.generator.JsonData">
    <!--
      WARNING - @mbg.generated
      This element is automatically generated by MyBatis Generator, do not modify.
    -->
    <id column="json_data_id" jdbcType="CHAR" property="jsonDataId" />
    <result column="json_data_relation_id" jdbcType="CHAR" property="jsonDataRelationId" />
    <result column="json_data_name" jdbcType="VARCHAR" property="jsonDataName" />
    <result column="json_data_request" jdbcType="VARCHAR" property="jsonDataRequest" />
    <result column="json_data_response" jdbcType="VARCHAR" property="jsonDataResponse" />
    <result column="json_data_create_time" jdbcType="TIMESTAMP" property="jsonDataCreateTime" />
    <result column="json_data_update_time" jdbcType="TIMESTAMP" property="jsonDataUpdateTime" />
    <result column="json_data_status" jdbcType="INTEGER" property="jsonDataStatus" />
  </resultMap>
  <sql id="Example_Where_Clause">
    <!--
      WARNING - @mbg.generated
      This element is automatically generated by MyBatis Generator, do not modify.
    -->
    <where>
      <foreach collection="oredCriteria" item="criteria" separator="or">
        <if test="criteria.valid">
          <trim prefix="(" prefixOverrides="and" suffix=")">
            <foreach collection="criteria.criteria" item="criterion">
              <choose>
                <when test="criterion.noValue">
                  and ${criterion.condition}
                </when>
                <when test="criterion.singleValue">
                  and ${criterion.condition} #{criterion.value}
                </when>
                <when test="criterion.betweenValue">
                  and ${criterion.condition} #{criterion.value} and #{criterion.secondValue}
                </when>
                <when test="criterion.listValue">
                  and ${criterion.condition}
                  <foreach close=")" collection="criterion.value" item="listItem" open="(" separator=",">
                    #{listItem}
                  </foreach>
                </when>
              </choose>
            </foreach>
          </trim>
        </if>
      </foreach>
    </where>
  </sql>
  <sql id="Update_By_Example_Where_Clause">
    <!--
      WARNING - @mbg.generated
      This element is automatically generated by MyBatis Generator, do not modify.
    -->
    <where>
      <foreach collection="example.oredCriteria" item="criteria" separator="or">
        <if test="criteria.valid">
          <trim prefix="(" prefixOverrides="and" suffix=")">
            <foreach collection="criteria.criteria" item="criterion">
              <choose>
                <when test="criterion.noValue">
                  and ${criterion.condition}
                </when>
                <when test="criterion.singleValue">
                  and ${criterion.condition} #{criterion.value}
                </when>
                <when test="criterion.betweenValue">
                  and ${criterion.condition} #{criterion.value} and #{criterion.secondValue}
                </when>
                <when test="criterion.listValue">
                  and ${criterion.condition}
                  <foreach close=")" collection="criterion.value" item="listItem" open="(" separator=",">
                    #{listItem}
                  </foreach>
                </when>
              </choose>
            </foreach>
          </trim>
        </if>
      </foreach>
    </where>
  </sql>
  <sql id="Base_Column_List">
    <!--
      WARNING - @mbg.generated
      This element is automatically generated by MyBatis Generator, do not modify.
    -->
    json_data_id, json_data_relation_id, json_data_name, json_data_request, json_data_response, 
    json_data_create_time, json_data_update_time, json_data_status
  </sql>
  <select id="selectByExample" parameterType="com.dllg.ebpay.model.generator.JsonDataExample" resultMap="BaseResultMap">
    <!--
      WARNING - @mbg.generated
      This element is automatically generated by MyBatis Generator, do not modify.
    -->
    select
    <if test="distinct">
      distinct
    </if>
    <include refid="Base_Column_List" />
    from json_data
    <if test="_parameter != null">
      <include refid="Example_Where_Clause" />
    </if>
    <if test="orderByClause != null">
      order by ${orderByClause}
    </if>
  </select>
  <select id="selectByPrimaryKey" parameterType="java.lang.String" resultMap="BaseResultMap">
    <!--
      WARNING - @mbg.generated
      This element is automatically generated by MyBatis Generator, do not modify.
    -->
    select 
    <include refid="Base_Column_List" />
    from json_data
    where json_data_id = #{jsonDataId,jdbcType=CHAR}
  </select>
  <delete id="deleteByPrimaryKey" parameterType="java.lang.String">
    <!--
      WARNING - @mbg.generated
      This element is automatically generated by MyBatis Generator, do not modify.
    -->
    delete from json_data
    where json_data_id = #{jsonDataId,jdbcType=CHAR}
  </delete>
  <delete id="deleteByExample" parameterType="com.dllg.ebpay.model.generator.JsonDataExample">
    <!--
      WARNING - @mbg.generated
      This element is automatically generated by MyBatis Generator, do not modify.
    -->
    delete from json_data
    <if test="_parameter != null">
      <include refid="Example_Where_Clause" />
    </if>
  </delete>
  <insert id="insert" parameterType="com.dllg.ebpay.model.generator.JsonData">
    <!--
      WARNING - @mbg.generated
      This element is automatically generated by MyBatis Generator, do not modify.
    -->
    insert into json_data (json_data_id, json_data_relation_id, json_data_name, 
      json_data_request, json_data_response, json_data_create_time, 
      json_data_update_time, json_data_status)
    values (#{jsonDataId,jdbcType=CHAR}, #{jsonDataRelationId,jdbcType=CHAR}, #{jsonDataName,jdbcType=VARCHAR}, 
      #{jsonDataRequest,jdbcType=VARCHAR}, #{jsonDataResponse,jdbcType=VARCHAR}, #{jsonDataCreateTime,jdbcType=TIMESTAMP}, 
      #{jsonDataUpdateTime,jdbcType=TIMESTAMP}, #{jsonDataStatus,jdbcType=INTEGER})
  </insert>
  <insert id="insertSelective" parameterType="com.dllg.ebpay.model.generator.JsonData">
    <!--
      WARNING - @mbg.generated
      This element is automatically generated by MyBatis Generator, do not modify.
    -->
    insert into json_data
    <trim prefix="(" suffix=")" suffixOverrides=",">
      <if test="jsonDataId != null">
        json_data_id,
      </if>
      <if test="jsonDataRelationId != null">
        json_data_relation_id,
      </if>
      <if test="jsonDataName != null">
        json_data_name,
      </if>
      <if test="jsonDataRequest != null">
        json_data_request,
      </if>
      <if test="jsonDataResponse != null">
        json_data_response,
      </if>
      <if test="jsonDataCreateTime != null">
        json_data_create_time,
      </if>
      <if test="jsonDataUpdateTime != null">
        json_data_update_time,
      </if>
      <if test="jsonDataStatus != null">
        json_data_status,
      </if>
    </trim>
    <trim prefix="values (" suffix=")" suffixOverrides=",">
      <if test="jsonDataId != null">
        #{jsonDataId,jdbcType=CHAR},
      </if>
      <if test="jsonDataRelationId != null">
        #{jsonDataRelationId,jdbcType=CHAR},
      </if>
      <if test="jsonDataName != null">
        #{jsonDataName,jdbcType=VARCHAR},
      </if>
      <if test="jsonDataRequest != null">
        #{jsonDataRequest,jdbcType=VARCHAR},
      </if>
      <if test="jsonDataResponse != null">
        #{jsonDataResponse,jdbcType=VARCHAR},
      </if>
      <if test="jsonDataCreateTime != null">
        #{jsonDataCreateTime,jdbcType=TIMESTAMP},
      </if>
      <if test="jsonDataUpdateTime != null">
        #{jsonDataUpdateTime,jdbcType=TIMESTAMP},
      </if>
      <if test="jsonDataStatus != null">
        #{jsonDataStatus,jdbcType=INTEGER},
      </if>
    </trim>
  </insert>
  <select id="countByExample" parameterType="com.dllg.ebpay.model.generator.JsonDataExample" resultType="java.lang.Long">
    <!--
      WARNING - @mbg.generated
      This element is automatically generated by MyBatis Generator, do not modify.
    -->
    select count(*) from json_data
    <if test="_parameter != null">
      <include refid="Example_Where_Clause" />
    </if>
  </select>
  <update id="updateByExampleSelective" parameterType="map">
    <!--
      WARNING - @mbg.generated
      This element is automatically generated by MyBatis Generator, do not modify.
    -->
    update json_data
    <set>
      <if test="record.jsonDataId != null">
        json_data_id = #{record.jsonDataId,jdbcType=CHAR},
      </if>
      <if test="record.jsonDataRelationId != null">
        json_data_relation_id = #{record.jsonDataRelationId,jdbcType=CHAR},
      </if>
      <if test="record.jsonDataName != null">
        json_data_name = #{record.jsonDataName,jdbcType=VARCHAR},
      </if>
      <if test="record.jsonDataRequest != null">
        json_data_request = #{record.jsonDataRequest,jdbcType=VARCHAR},
      </if>
      <if test="record.jsonDataResponse != null">
        json_data_response = #{record.jsonDataResponse,jdbcType=VARCHAR},
      </if>
      <if test="record.jsonDataCreateTime != null">
        json_data_create_time = #{record.jsonDataCreateTime,jdbcType=TIMESTAMP},
      </if>
      <if test="record.jsonDataUpdateTime != null">
        json_data_update_time = #{record.jsonDataUpdateTime,jdbcType=TIMESTAMP},
      </if>
      <if test="record.jsonDataStatus != null">
        json_data_status = #{record.jsonDataStatus,jdbcType=INTEGER},
      </if>
    </set>
    <if test="_parameter != null">
      <include refid="Update_By_Example_Where_Clause" />
    </if>
  </update>
  <update id="updateByExample" parameterType="map">
    <!--
      WARNING - @mbg.generated
      This element is automatically generated by MyBatis Generator, do not modify.
    -->
    update json_data
    set json_data_id = #{record.jsonDataId,jdbcType=CHAR},
      json_data_relation_id = #{record.jsonDataRelationId,jdbcType=CHAR},
      json_data_name = #{record.jsonDataName,jdbcType=VARCHAR},
      json_data_request = #{record.jsonDataRequest,jdbcType=VARCHAR},
      json_data_response = #{record.jsonDataResponse,jdbcType=VARCHAR},
      json_data_create_time = #{record.jsonDataCreateTime,jdbcType=TIMESTAMP},
      json_data_update_time = #{record.jsonDataUpdateTime,jdbcType=TIMESTAMP},
      json_data_status = #{record.jsonDataStatus,jdbcType=INTEGER}
    <if test="_parameter != null">
      <include refid="Update_By_Example_Where_Clause" />
    </if>
  </update>
  <update id="updateByPrimaryKeySelective" parameterType="com.dllg.ebpay.model.generator.JsonData">
    <!--
      WARNING - @mbg.generated
      This element is automatically generated by MyBatis Generator, do not modify.
    -->
    update json_data
    <set>
      <if test="jsonDataRelationId != null">
        json_data_relation_id = #{jsonDataRelationId,jdbcType=CHAR},
      </if>
      <if test="jsonDataName != null">
        json_data_name = #{jsonDataName,jdbcType=VARCHAR},
      </if>
      <if test="jsonDataRequest != null">
        json_data_request = #{jsonDataRequest,jdbcType=VARCHAR},
      </if>
      <if test="jsonDataResponse != null">
        json_data_response = #{jsonDataResponse,jdbcType=VARCHAR},
      </if>
      <if test="jsonDataCreateTime != null">
        json_data_create_time = #{jsonDataCreateTime,jdbcType=TIMESTAMP},
      </if>
      <if test="jsonDataUpdateTime != null">
        json_data_update_time = #{jsonDataUpdateTime,jdbcType=TIMESTAMP},
      </if>
      <if test="jsonDataStatus != null">
        json_data_status = #{jsonDataStatus,jdbcType=INTEGER},
      </if>
    </set>
    where json_data_id = #{jsonDataId,jdbcType=CHAR}
  </update>
  <update id="updateByPrimaryKey" parameterType="com.dllg.ebpay.model.generator.JsonData">
    <!--
      WARNING - @mbg.generated
      This element is automatically generated by MyBatis Generator, do not modify.
    -->
    update json_data
    set json_data_relation_id = #{jsonDataRelationId,jdbcType=CHAR},
      json_data_name = #{jsonDataName,jdbcType=VARCHAR},
      json_data_request = #{jsonDataRequest,jdbcType=VARCHAR},
      json_data_response = #{jsonDataResponse,jdbcType=VARCHAR},
      json_data_create_time = #{jsonDataCreateTime,jdbcType=TIMESTAMP},
      json_data_update_time = #{jsonDataUpdateTime,jdbcType=TIMESTAMP},
      json_data_status = #{jsonDataStatus,jdbcType=INTEGER}
    where json_data_id = #{jsonDataId,jdbcType=CHAR}
  </update>
</mapper>